{
	"2013-04-16 16:00:00":
	{
		"team-1":
		{
			"name":"Punjab",
			"imageUrl":"/images/rummy.tld/kings-11-punjab.png"
		},
		"team-2":
		{
			"name":"Kolkata",
			"imageUrl":"/images/rummy.tld/kolkata-knight-riders.png"
		},
		"vote":
		{
			"voteNumber":"KXP_KKR_2013-04-16"
		}
	},
	"2013-04-16 20:00:00":
	{
		"team-1":
		{
			"name":"Bangalore",
			"imageUrl":"/images/rummy.tld/royal-challengers-bangalore.png"
		},
		"team-2":
		{
			"name":"Delhi",
			"imageUrl":"/images/rummy.tld/delhi-daredevils.png"
		},
		"vote":
		{
			"voteNumber":"RCB_DD_2013-04-16"
		}
	},
	"2013-04-17 16:00:00":
	{
		"team-1":
		{
			"name":"Pune",
			"imageUrl":"/images/rummy.tld/sahara-pune-warriors.png"
		},
		"team-2":
		{
			"name":"Hyderabad",
			"imageUrl":"/images/rummy.tld/sunrisers-hyderabad.png"
		},
		"vote":
		{
			"voteNumber":"PWI_SH_2013-04-17"
		}
	},
	"2013-04-17 20:00:00":
	{
		"team-1":
		{
			"name":"Rajsthan",
			"imageUrl":"/images/rummy.tld/rajasthan-royals.png"
		},
		"team-2":
		{
			"name":"Mumbai",
			"imageUrl":"/images/rummy.tld/mumbai-indians.png"
		},
		"vote":
		{
			"voteNumber":"RR_MI_2013-04-17"
		}
	},
	"2013-04-18 20:00:00":
	{
		"team-1":
		{
			"name":"Delhi",
			"imageUrl":"/images/rummy.tld/delhi-daredevils.png"
		},
		"team-2":
		{
			"name":"Chennai",
			"imageUrl":"/images/rummy.tld/chennai-super-kings.png"
		},
		"vote":
		{
			"voteNumber":"DD_CSK_2013-04-18"
		}
	},
	"2013-04-19 20:00:00":
	{
		"team-1":
		{
			"name":"Hyderabad",
			"imageUrl":"/images/rummy.tld/sunrisers-hyderabad.png"
		},
		"team-2":
		{
			"name":"Punjab",
			"imageUrl":"/images/rummy.tld/kings-11-punjab.png"
		},
		"vote":
		{
			"voteNumber":"SH_KXP_2013-04-19"
		}
	},
	"2013-04-20 16:00:00":
	{
		"team-1":
		{
			"name":"Kolkata",
			"imageUrl":"/images/rummy.tld/kolkata-knight-riders.png"
		},
		"team-2":
		{
			"name":"Chennai",
			"imageUrl":"/images/rummy.tld/chennai-super-kings.png"
		},
		"vote":
		{
			"voteNumber":"KKR_CSK_2013-04-20"
		}
	},
	"2013-04-20 20:00:00":
	{
		"team-1":
		{
			"name":"Bangalore",
			"imageUrl":"/images/rummy.tld/royal-challengers-bangalore.png"
		},
		"team-2":
		{
			"name":"Rajsthan",
			"imageUrl":"/images/rummy.tld/rajasthan-royals.png"
		},
		"vote":
		{
			"voteNumber":"RCB_RR_2013-04-20"
		}
	},
	"2013-04-21 16:00:00":
	{
		"team-1":
		{
			"name":"Delhi",
			"imageUrl":"/images/rummy.tld/delhi-daredevils.png"
		},
		"team-2":
		{
			"name":"Mumbai",
			"imageUrl":"/images/rummy.tld/mumbai-indians.png"
		},
		"vote":
		{
			"voteNumber":"DD_MI_2013-04-21"
		}
	},
	"2013-04-21 20:00:00":
	{
		"team-1":
		{
			"name":"Punjab",
			"imageUrl":"/images/rummy.tld/kings-11-punjab.png"
		},
		"team-2":
		{
			"name":"Pune",
			"imageUrl":"/images/rummy.tld/sahara-pune-warriors.png"
		},
		"vote":
		{
			"voteNumber":"KXP_PWI_2013-04-21"
		}
	},
	"2013-04-22 20:00:00":
	{
		"team-1":
		{
			"name":"Chennai",
			"imageUrl":"/images/rummy.tld/chennai-super-kings.png"
		},
		"team-2":
		{
			"name":"Rajsthan",
			"imageUrl":"/images/rummy.tld/rajasthan-royals.png"
		},
		"vote":
		{
			"voteNumber":"CSK_RR_2013-04-22"
		}
	},
	"2013-04-23 16:00:00":
	{
		"team-1":
		{
			"name":"Bangalore",
			"imageUrl":"/images/rummy.tld/royal-challengers-bangalore.png"
		},
		"team-2":
		{
			"name":"Pune",
			"imageUrl":"/images/rummy.tld/sahara-pune-warriors.png"
		},
		"vote":
		{
			"voteNumber":"RCB_PWI_2013-04-23"
		}
	},
	"2013-04-23 20:00:00":
	{
		"team-1":
		{
			"name":"Delhi",
			"imageUrl":"/images/rummy.tld/delhi-daredevils.png"
		},
		"team-2":
		{
			"name":"Punjab",
			"imageUrl":"/images/rummy.tld/kings-11-punjab.png"
		},
		"vote":
		{
			"voteNumber":"DD_KXP_2013-04-23"
		}
	},
	"2013-04-24 20:00:00":
	{
		"team-1":
		{
			"name":"Kolkata",
			"imageUrl":"/images/rummy.tld/kolkata-knight-riders.png"
		},
		"team-2":
		{
			"name":"Mumbai",
			"imageUrl":"/images/rummy.tld/mumbai-indians.png"
		},
		"vote":
		{
			"voteNumber":"KKR_MI_2013-04-24"
		}
	},
	"2013-04-25 20:00:00":
	{
		"team-1":
		{
			"name":"Chennai",
			"imageUrl":"/images/rummy.tld/chennai-super-kings.png"
		},
		"team-2":
		{
			"name":"Hyderabad",
			"imageUrl":"/images/rummy.tld/sunrisers-hyderabad.png"
		},
		"vote":
		{
			"voteNumber":"CSK_SH_2013-04-25"
		}
	},
	"2013-04-26 20:00:00":
	{
		"team-1":
		{
			"name":"Kolkata",
			"imageUrl":"/images/rummy.tld/kolkata-knight-riders.png"
		},
		"team-2":
		{
			"name":"Punjab",
			"imageUrl":"/images/rummy.tld/kings-11-punjab.png"
		},
		"vote":
		{
			"voteNumber":"KKR_KXP_2013-04-26"
		}
	},
	"2013-04-27 16:00:00":
	{
		"team-1":
		{
			"name":"Rajsthan",
			"imageUrl":"/images/rummy.tld/rajasthan-royals.png"
		},
		"team-2":
		{
			"name":"Hyderabad",
			"imageUrl":"/images/rummy.tld/sunrisers-hyderabad.png"
		},
		"vote":
		{
			"voteNumber":"RR_SH_2013-04-27"
		}
	},
	"2013-04-27 20:00:00":
	{
		"team-1":
		{
			"name":"Mumbai",
			"imageUrl":"/images/rummy.tld/mumbai-indians.png"
		},
		"team-2":
		{
			"name":"Bangalore",
			"imageUrl":"/images/rummy.tld/royal-challengers-bangalore.png"
		},
		"vote":
		{
			"voteNumber":"MI_RCB_2013-04-27"
		}
	},
	"2013-04-28 16:00:00":
	{
		"team-1":
		{
			"name":"Chennai",
			"imageUrl":"/images/rummy.tld/chennai-super-kings.png"
		},
		"team-2":
		{
			"name":"Kolkata",
			"imageUrl":"/images/rummy.tld/kolkata-knight-riders.png"
		},
		"vote":
		{
			"voteNumber":"CSK_KKR_2013-04-28"
		}
	},
	"2013-04-28 20:00:00":
	{
		"team-1":
		{
			"name":"Delhi",
			"imageUrl":"/images/rummy.tld/delhi-daredevils.png"
		},
		"team-2":
		{
			"name":"Pune",
			"imageUrl":"/images/rummy.tld/sahara-pune-warriors.png"
		},
		"vote":
		{
			"voteNumber":"DD_PWI_2013-04-28"
		}
	},
	"2013-04-29 16:00:00":
	{
		"team-1":
		{
			"name":"Rajsthan",
			"imageUrl":"/images/rummy.tld/rajasthan-royals.png"
		},
		"team-2":
		{
			"name":"Bangalore",
			"imageUrl":"/images/rummy.tld/royal-challengers-bangalore.png"
		},
		"vote":
		{
			"voteNumber":"RR_RCB_2013-04-29"
		}
	},
	"2013-04-29 20:00:00":
	{
		"team-1":
		{
			"name":"Mumbai",
			"imageUrl":"/images/rummy.tld/mumbai-indians.png"
		},
		"team-2":
		{
			"name":"Punjab",
			"imageUrl":"/images/rummy.tld/kings-11-punjab.png"
		},
		"vote":
		{
			"voteNumber":"MI_KXP_2013-04-29"
		}
	},
	"2013-04-30 20:00:00":
	{
		"team-1":
		{
			"name":"Pune",
			"imageUrl":"/images/rummy.tld/sahara-pune-warriors.png"
		},
		"team-2":
		{
			"name":"Chennai",
			"imageUrl":"/images/rummy.tld/chennai-super-kings.png"
		},
		"vote":
		{
			"voteNumber":"PWI_CSK_2013-04-30"
		}
	},
	"2013-05-01 16:00:00":
	{
		"team-1":
		{
			"name":"Hyderabad",
			"imageUrl":"/images/rummy.tld/sunrisers-hyderabad.png"
		},
		"team-2":
		{
			"name":"Mumbai",
			"imageUrl":"/images/rummy.tld/mumbai-indians.png"
		},
		"vote":
		{
			"voteNumber":"SH_MI_2013-05-01"
		}
	},
	"2013-05-01 20:00:00":
	{
		"team-1":
		{
			"name":"Delhi",
			"imageUrl":"/images/rummy.tld/delhi-daredevils.png"
		},
		"team-2":
		{
			"name":"Kolkata",
			"imageUrl":"/images/rummy.tld/kolkata-knight-riders.png"
		},
		"vote":
		{
			"voteNumber":"DD_KKR_2013-05-01"
		}
	},
	"2013-05-02 16:00:00":
	{
		"team-1":
		{
			"name":"Chennai",
			"imageUrl":"/images/rummy.tld/chennai-super-kings.png"
		},
		"team-2":
		{
			"name":"Punjab",
			"imageUrl":"/images/rummy.tld/kings-11-punjab.png"
		},
		"vote":
		{
			"voteNumber":"CSK_KXP_2013-05-02"
		}
	},
	"2013-05-02 20:00:00":
	{
		"team-1":
		{
			"name":"Pune",
			"imageUrl":"/images/rummy.tld/sahara-pune-warriors.png"
		},
		"team-2":
		{
			"name":"Bangalore",
			"imageUrl":"/images/rummy.tld/royal-challengers-bangalore.png"
		},
		"vote":
		{
			"voteNumber":"PWI_RCB_2013-05-02"
		}
	},
	"2013-05-03 20:00:00":
	{
		"team-1":
		{
			"name":"Kolkata",
			"imageUrl":"/images/rummy.tld/kolkata-knight-riders.png"
		},
		"team-2":
		{
			"name":"Rajsthan",
			"imageUrl":"/images/rummy.tld/rajasthan-royals.png"
		},
		"vote":
		{
			"voteNumber":"KKR_RR_2013-05-03"
		}
	},
	"2013-05-04 20:00:00":
	{
		"team-1":
		{
			"name":"Hyderabad",
			"imageUrl":"/images/rummy.tld/sunrisers-hyderabad.png"
		},
		"team-2":
		{
			"name":"Delhi",
			"imageUrl":"/images/rummy.tld/delhi-daredevils.png"
		},
		"vote":
		{
			"voteNumber":"SH_DD_2013-05-04"
		}
	},
	"2013-05-05 16:00:00":
	{
		"team-1":
		{
			"name":"Mumbai",
			"imageUrl":"/images/rummy.tld/mumbai-indians.png"
		},
		"team-2":
		{
			"name":"Chennai",
			"imageUrl":"/images/rummy.tld/chennai-super-kings.png"
		},
		"vote":
		{
			"voteNumber":"MI_CSK_2013-05-05"
		}
	},
	"2013-05-05 20:00:00":
	{
		"team-1":
		{
			"name":"Rajsthan",
			"imageUrl":"/images/rummy.tld/rajasthan-royals.png"
		},
		"team-2":
		{
			"name":"Pune",
			"imageUrl":"/images/rummy.tld/sahara-pune-warriors.png"
		},
		"vote":
		{
			"voteNumber":"RR_PWI_2013-05-05"
		}
	},
	"2013-05-06 20:00:00":
	{
		"team-1":
		{
			"name":"Punjab",
			"imageUrl":"/images/rummy.tld/kings-11-punjab.png"
		},
		"team-2":
		{
			"name":"Bangalore",
			"imageUrl":"/images/rummy.tld/royal-challengers-bangalore.png"
		},
		"vote":
		{
			"voteNumber":"KXP_RCB_2013-05-06"
		}
	},
	"2013-05-07 16:00:00":
	{
		"team-1":
		{
			"name":"Rajsthan",
			"imageUrl":"/images/rummy.tld/rajasthan-royals.png"
		},
		"team-2":
		{
			"name":"Delhi",
			"imageUrl":"/images/rummy.tld/delhi-daredevils.png"
		},
		"vote":
		{
			"voteNumber":"RR_DD_2013-05-07"
		}
	},
	"2013-05-07 20:00:00":
	{
		"team-1":
		{
			"name":"Mumbai",
			"imageUrl":"/images/rummy.tld/mumbai-indians.png"
		},
		"team-2":
		{
			"name":"Kolkata",
			"imageUrl":"/images/rummy.tld/kolkata-knight-riders.png"
		},
		"vote":
		{
			"voteNumber":"MI_KKR_2013-05-07"
		}
	},
	"2013-05-08 20:00:00":
	{
		"team-1":
		{
			"name":"Hyderabad",
			"imageUrl":"/images/rummy.tld/sunrisers-hyderabad.png"
		},
		"team-2":
		{
			"name":"Chennai",
			"imageUrl":"/images/rummy.tld/chennai-super-kings.png"
		},
		"vote":
		{
			"voteNumber":"SH_CSK_2013-05-08"
		}
	},
	"2013-05-09 16:00:00":
	{
		"team-1":
		{
			"name":"Punjab",
			"imageUrl":"/images/rummy.tld/kings-11-punjab.png"
		},
		"team-2":
		{
			"name":"Rajsthan",
			"imageUrl":"/images/rummy.tld/rajasthan-royals.png"
		},
		"vote":
		{
			"voteNumber":"KXP_RR_2013-05-09"
		}
	},
	"2013-05-09 20:00:00":
	{
		"team-1":
		{
			"name":"Pune",
			"imageUrl":"/images/rummy.tld/sahara-pune-warriors.png"
		},
		"team-2":
		{
			"name":"Kolkata",
			"imageUrl":"/images/rummy.tld/kolkata-knight-riders.png"
		},
		"vote":
		{
			"voteNumber":"PWI_KKR_2013-05-09"
		}
	},
	"2013-05-10 20:00:00":
	{
		"team-1":
		{
			"name":"Delhi",
			"imageUrl":"/images/rummy.tld/delhi-daredevils.png"
		},
		"team-2":
		{
			"name":"Bangalore",
			"imageUrl":"/images/rummy.tld/royal-challengers-bangalore.png"
		},
		"vote":
		{
			"voteNumber":"DD_RCB_2013-05-10"
		}
	},
	"2013-05-11 16:00:00":
	{
		"team-1":
		{
			"name":"Pune",
			"imageUrl":"/images/rummy.tld/sahara-pune-warriors.png"
		},
		"team-2":
		{
			"name":"Mumbai",
			"imageUrl":"/images/rummy.tld/mumbai-indians.png"
		},
		"vote":
		{
			"voteNumber":"PWI_MI_2013-05-11"
		}
	},
	"2013-05-11 20:00:00":
	{
		"team-1":
		{
			"name":"Punjab",
			"imageUrl":"/images/rummy.tld/kings-11-punjab.png"
		},
		"team-2":
		{
			"name":"Hyderabad",
			"imageUrl":"/images/rummy.tld/sunrisers-hyderabad.png"
		},
		"vote":
		{
			"voteNumber":"KXP_SH_2013-05-11"
		}
	},
	"2013-05-12 16:00:00":
	{
		"team-1":
		{
			"name":"Kolkata",
			"imageUrl":"/images/rummy.tld/kolkata-knight-riders.png"
		},
		"team-2":
		{
			"name":"Bangalore",
			"imageUrl":"/images/rummy.tld/royal-challengers-bangalore.png"
		},
		"vote":
		{
			"voteNumber":"KKR_RCB_2013-05-12"
		}
	},
	"2013-05-12 20:00:00":
	{
		"team-1":
		{
			"name":"Rajsthan",
			"imageUrl":"/images/rummy.tld/rajasthan-royals.png"
		},
		"team-2":
		{
			"name":"Chennai",
			"imageUrl":"/images/rummy.tld/chennai-super-kings.png"
		},
		"vote":
		{
			"voteNumber":"RR_CSK_2013-05-12"
		}
	},
	"2013-05-13 20:00:00":
	{
		"team-1":
		{
			"name":"Mumbai",
			"imageUrl":"/images/rummy.tld/mumbai-indians.png"
		},
		"team-2":
		{
			"name":"Hyderabad",
			"imageUrl":"/images/rummy.tld/sunrisers-hyderabad.png"
		},
		"vote":
		{
			"voteNumber":"MI_SH_2013-05-13"
		}
	},
	"2013-05-14 16:00:00":
	{
		"team-1":
		{
			"name":"Bangalore",
			"imageUrl":"/images/rummy.tld/royal-challengers-bangalore.png"
		},
		"team-2":
		{
			"name":"Punjab",
			"imageUrl":"/images/rummy.tld/kings-11-punjab.png"
		},
		"vote":
		{
			"voteNumber":"RCB_KXP_2013-05-14"
		}
	},
	"2013-05-14 20:00:00":
	{
		"team-1":
		{
			"name":"Chennai",
			"imageUrl":"/images/rummy.tld/chennai-super-kings.png"
		},
		"team-2":
		{
			"name":"Delhi",
			"imageUrl":"/images/rummy.tld/delhi-daredevils.png"
		},
		"vote":
		{
			"voteNumber":"CSK_DD_2013-05-14"
		}
	},
	"2013-05-15 16:00:00":
	{
		"team-1":
		{
			"name":"Kolkata",
			"imageUrl":"/images/rummy.tld/kolkata-knight-riders.png"
		},
		"team-2":
		{
			"name":"Pune",
			"imageUrl":"/images/rummy.tld/sahara-pune-warriors.png"
		},
		"vote":
		{
			"voteNumber":"KKR_PWI_2013-05-15"
		}
	},
	"2013-05-15 20:00:00":
	{
		"team-1":
		{
			"name":"Mumbai",
			"imageUrl":"/images/rummy.tld/mumbai-indians.png"
		},
		"team-2":
		{
			"name":"Rajsthan",
			"imageUrl":"/images/rummy.tld/rajasthan-royals.png"
		},
		"vote":
		{
			"voteNumber":"MI_RR_2013-05-15"
		}
	},
	"2013-05-16 20:00:00":
	{
		"team-1":
		{
			"name":"Punjab",
			"imageUrl":"/images/rummy.tld/kings-11-punjab.png"
		},
		"team-2":
		{
			"name":"Delhi",
			"imageUrl":"/images/rummy.tld/delhi-daredevils.png"
		},
		"vote":
		{
			"voteNumber":"KXP_DD_2013-05-16"
		}
	},
	"2013-05-17 20:00:00":
	{
		"team-1":
		{
			"name":"Hyderabad",
			"imageUrl":"/images/rummy.tld/sunrisers-hyderabad.png"
		},
		"team-2":
		{
			"name":"Rajsthan",
			"imageUrl":"/images/rummy.tld/rajasthan-royals.png"
		},
		"vote":
		{
			"voteNumber":"SH_RR_2013-05-17"
		}
	},
	"2013-05-18 16:00:00":
	{
		"team-1":
		{
			"name":"Punjab",
			"imageUrl":"/images/rummy.tld/kings-11-punjab.png"
		},
		"team-2":
		{
			"name":"Mumbai",
			"imageUrl":"/images/rummy.tld/mumbai-indians.png"
		},
		"vote":
		{
			"voteNumber":"KXP_MI_2013-05-18"
		}
	},
	"2013-05-18 20:00:00":
	{
		"team-1":
		{
			"name":"Bangalore",
			"imageUrl":"/images/rummy.tld/royal-challengers-bangalore.png"
		},
		"team-2":
		{
			"name":"Chennai",
			"imageUrl":"/images/rummy.tld/chennai-super-kings.png"
		},
		"vote":
		{
			"voteNumber":"RCB_CSK_2013-05-18"
		}
	},
	"2013-05-19 16:00:00":
	{
		"team-1":
		{
			"name":"Pune",
			"imageUrl":"/images/rummy.tld/sahara-pune-warriors.png"
		},
		"team-2":
		{
			"name":"Delhi",
			"imageUrl":"/images/rummy.tld/delhi-daredevils.png"
		},
		"vote":
		{
			"voteNumber":"PWI_DD_2013-05-19"
		}
	},
	"2013-05-19 20:00:00":
	{
		"team-1":
		{
			"name":"Hyderabad",
			"imageUrl":"/images/rummy.tld/sunrisers-hyderabad.png"
		},
		"team-2":
		{
			"name":"Kolkata",
			"imageUrl":"/images/rummy.tld/kolkata-knight-riders.png"
		},
		"vote":
		{
			"voteNumber":"SH_KKR_2013-05-19"
		}
	},
	"2013-05-21 20:00:00":
	{
		"team-1":
		{
			"name":"Chennai",
			"imageUrl":"/images/rummy.tld/chennai-super-kings.png"
		},
		"team-2":
		{
			"name":"Mumbai",
			"imageUrl":"/images/rummy.tld/mumbai-indians.png"
		},
		"vote":
		{
			"voteNumber":"CSK_MI_2013-05-21"
		}
	},
	"2013-05-22 20:00:00":
	{
		"team-1":
		{
			"name":"Rajsthan",
			"imageUrl":"/images/rummy.tld/rajasthan-royals.png"
		},
		"team-2":
		{
			"name":"Hyderabad",
			"imageUrl":"/images/rummy.tld/sunrisers-hyderabad.png"
		},
		"vote":
		{
			"voteNumber":"RR_SH_2013-05-22"
		}
	},
	"2013-05-24 20:00:00":
	{
		"team-1":
		{
			"name":"Rajsthan",
			"imageUrl":"/images/rummy.tld/rajasthan-royals.png"
		},
		"team-2":
		{
			"name":"Mumbai",
			"imageUrl":"/images/rummy.tld/mumbai-indians.png"
		},
		"vote":
		{
			"voteNumber":"RR_MI_2013-05-24"
		}
	}
}