{
	"Allahabad Bank":"280",
	"Axis Bank":"50",
	"Bank of Bahrain and Kuwait":"340",
	"Bank of Baroda":"310",
	"Bank of India":"240",
	"Bank of Maharashtra":"750",
	"Canara Bank":"930",
	"Catholic Syrian Bank":"1130",
	"Central Bank of India":"740",
	"City Union Bank":"440",
	"Corporation Bank":"120",
	"Development Credit Bank":"540",
	"Deutsche Bank":"330",
	"Dhanlaxmi Bank":"370",
	"Federal Bank":"270",
	"Indian Bank":"490",
	"Indian Overseas Bank":"420",
	"ING Vysya Bank":"830",
	"J&K Bank":"350",
	"Karnataka Bank":"140",
	"Karur Vysya Bank":"760",
	"Kotak Mahindra Bank":"910",
	"Oriental Bank of Commerce":"160",
	"Punjab National Bank":"1220",
	"South Indian Bank":"180",
	"Standard Chartered Bank":"450",
	"State Bank Of Bikaner and & Jaipur":"950",
	"State Bank of Hyderabad":"560",
	"State Bank of India":"530",
	"State Bank of Mysore":"550",
	"State Bank of Patiala":"880",
	"State Bank of Travencore":"680",
	"Tamilnad Mercantile Bank":"620",
	"Union Bank of India":"190",
	"United Bank of India":"570",
	"Vijaya Bank":"200",
	"Yes Bank":"130"
}